Workbook

Sheet Characters
A1: ID | B1: Name | C1: Category | D1: Description | E1: Gender | F1: Nationality | G1: Birth Year | H1: Popularity (1-100) | I1: Active | J1: Retired | K1: Profession | L1: Sport | M1: Team | N1: League | O1: Position | P1: Athlete | Q1: Captain | R1: Batsman | S1: Bowler | T1: All-Rounder | U1: Wicketkeeper | V1: World Cup Winner | W1: Champions League Winner | X1: Olympic Medalist | Y1: Major Champion | Z1: Actor | AA1: Actress | AB1: Singer | AC1: Director | AD1: Known for Comedy | AE1: Marvel | AF1: Oscar Winner | AG1: Grammy Winner | AH1: Solo Artist | AI1: Band Member | AJ1: Entrepreneur | AK1: Founder | AL1: Billionaire | AM1: Streamer/YouTuber | AN1: Indian | AO1: American | AP1: British | AQ1: European | AR1: Fictional | AS1: Fictional Origin | AT1: Hero/Villain
A2: fb-hegerberg | B2: Ada Hegerberg | C2: Footballers | D2: Norwegian forward, women's football | E2: female | F2: Norway | G2: 1995 | H2: 60 | I2: =TRUE() | J2: =FALSE() | K2: Footballer | L2: Football | M2: Olympique Lyonnais | N2: Division 1 Féminine | O2: Forward | P2: =TRUE() | Q2: =FALSE() | V2: =FALSE() | W2: =TRUE() | AQ2: =TRUE()
A3: fb-alexmorgan | B3: Alex Morgan | C3: Footballers | D3: American forward, women's football, retired | E3: female | F3: USA | G3: 1989 | H3: 60 | I3: =FALSE() | J3: =TRUE() | K3: Footballer | L3: Football | M3: San Diego Wave | N3: NWSL | O3: Forward | P3: =TRUE() | Q3: =FALSE() | V3: =TRUE() | AO3: =TRUE() | AQ3: =FALSE()
A4: fb-alisson | B4: Alisson Becker | C4: Footballers | D4: Brazilian goalkeeper, Liverpool FC | E4: male | F4: Brazil | G4: 1992 | H4: 60 | I4: =TRUE() | J4: =FALSE() | K4: Footballer | L4: Football | M4: Liverpool FC | N4: Premier League | O4: Goalkeeper | P4: =TRUE() | Q4: =FALSE() | V4: =FALSE() | W4: =TRUE() | AQ4: =FALSE()
A5: fb-pirlo | B5: Andrea Pirlo | C5: Footballers | D5: Italian midfielder, retired | E5: male | F5: Italy | G5: 1979 | H5: 60 | I5: =FALSE() | J5: =TRUE() | K5: Footballer | L5: Football | M5: Juventus | N5: Serie A | O5: Midfielder | P5: =TRUE() | Q5: =FALSE() | V5: =TRUE() | W5: =TRUE() | AQ5: =TRUE()
A6: fb-iniesta | B6: Andrés Iniesta | C6: Footballers | D6: Spanish midfielder, retired from Europe | E6: male | F6: Spain | G6: 1984 | H6: 60 | I6: =TRUE() | J6: =FALSE() | K6: Footballer | L6: Football | M6: Emirates Club | N6: UAE Pro League | O6: Midfielder | P6: =TRUE() | Q6: =FALSE() | V6: =TRUE() | W6: =TRUE() | AQ6: =TRUE()
A7: fb-griezmann | B7: Antoine Griezmann | C7: Footballers | D7: French forward, Atlético Madrid | E7: male | F7: France | G7: 1991 | H7: 60 | I7: =TRUE() | J7: =FALSE() | K7: Footballer | L7: Football | M7: Atlético Madrid | N7: La Liga | O7: Forward | P7: =TRUE() | Q7: =FALSE() | V7: =TRUE() | W7: =FALSE() | AQ7: =TRUE()
A8: fb-saka | B8: Bukayo Saka | C8: Footballers | D8: English forward, Arsenal FC | E8: male | F8: England | G8: 2001 | H8: 60 | I8: =TRUE() | J8: =FALSE() | K8: Footballer | L8: Football | M8: Arsenal FC | N8: Premier League | O8: Forward | P8: =TRUE() | Q8: =FALSE() | V8: =FALSE() | W8: =FALSE() | AP8: =TRUE() | AQ8: =TRUE()
A9: fb-ronaldo-cr7 | B9: Cristiano Ronaldo | C9: Footballers | D9: Portuguese forward, Al Nassr FC | E9: male | F9: Portugal | G9: 1985 | H9: 99 | I9: =TRUE() | J9: =FALSE() | K9: Footballer | L9: Football | M9: Al Nassr FC | N9: Saudi Pro League | O9: Forward | P9: =TRUE() | Q9: =TRUE() | V9: =FALSE() | W9: =TRUE() | AQ9: =TRUE()
A10: fb-beckham | B10: David Beckham | C10: Footballers | D10: English former midfielder, now club owner | E10: male | F10: England | G10: 1975 | H10: 87 | I10: =FALSE() | J10: =TRUE() | K10: Footballer; Entrepreneur | L10: Football | M10: Manchester United | N10: Premier League | O10: Midfielder | P10: =TRUE() | Q10: =TRUE() | V10: =FALSE() | W10: =TRUE() | AJ10: =TRUE() | AP10: =TRUE() | AQ10: =TRUE()
A11: fb-drogba | B11: Didier Drogba | C11: Footballers | D11: Ivorian former forward | E11: male | F11: Ivory Coast | G11: 1978 | H11: 60 | I11: =FALSE() | J11: =TRUE() | K11: Footballer | L11: Football | M11: Chelsea FC | N11: Premier League | O11: Forward | P11: =TRUE() | Q11: =TRUE() | V11: =FALSE() | W11: =TRUE() | AQ11: =FALSE()
A12: fb-maradona | B12: Diego Maradona | C12: Footballers | D12: Argentine football legend | E12: male | F12: Argentina | G12: 1960 | H12: 95 | I12: =FALSE() | J12: =TRUE() | K12: Footballer | L12: Football | M12: Napoli | N12: Serie A | O12: Forward | P12: =TRUE() | Q12: =TRUE() | V12: =TRUE() | W12: =FALSE() | AQ12: =FALSE()
A13: fb-ederson | B13: Ederson | C13: Footballers | D13: Brazilian goalkeeper, Manchester City | E13: male | F13: Brazil | G13: 1993 | H13: 60 | I13: =TRUE() | J13: =FALSE() | K13: Footballer | L13: Football | M13: Manchester City | N13: Premier League | O13: Goalkeeper | P13: =TRUE() | Q13: =FALSE() | V13: =FALSE() | W13: =TRUE() | AQ13: =FALSE()
A14: fb-cavani | B14: Edinson Cavani | C14: Footballers | D14: Uruguayan forward | E14: male | F14: Uruguay | G14: 1987 | H14: 60 | I14: =TRUE() | J14: =FALSE() | K14: Footballer | L14: Football | M14: Boca Juniors | N14: Argentine Primera División | O14: Forward | P14: =TRUE() | Q14: =FALSE() | V14: =FALSE() | W14: =FALSE() | AQ14: =FALSE()
A15: fb-haaland | B15: Erling Haaland | C15: Footballers | D15: Norwegian forward, Manchester City | E15: male | F15: Norway | G15: 2000 | H15: 88 | I15: =TRUE() | J15: =FALSE() | K15: Footballer | L15: Football | M15: Manchester City | N15: Premier League | O15: Forward | P15: =TRUE() | Q15: =FALSE() | V15: =FALSE() | W15: =TRUE() | AQ15: =TRUE()
A16: fb-eusebio | B16: Eusébio | C16: Footballers | D16: Portuguese football legend | E16: male | F16: Portugal | G16: 1942 | H16: 60 | I16: =FALSE() | J16: =TRUE() | K16: Footballer | L16: Football | M16: Benfica | N16: Primeira Liga | O16: Forward | P16: =TRUE() | Q16: =FALSE() | V16: =FALSE() | W16: =TRUE() | AQ16: =TRUE()
A17: fb-beckenbauer | B17: Franz Beckenbauer | C17: Footballers | D17: German football legend, defender | E17: male | F17: Germany | G17: 1945 | H17: 60 | I17: =FALSE() | J17: =TRUE() | K17: Footballer | L17: Football | M17: Bayern Munich | N17: Bundesliga | O17: Defender | P17: =TRUE() | Q17: =TRUE() | V17: =TRUE() | W17: =TRUE() | AQ17: =TRUE()
A18: fb-defrenkie | B18: Frenkie de Jong | C18: Footballers | D18: Dutch midfielder, FC Barcelona | E18: male | F18: Netherlands | G18: 1997 | H18: 60 | I18: =TRUE() | J18: =FALSE() | K18: Footballer | L18: Football | M18: FC Barcelona | N18: La Liga | O18: Midfielder | P18: =TRUE() | Q18: =FALSE() | V18: =FALSE() | W18: =FALSE() | AQ18: =TRUE()
A19: fb-georgebest | B19: George Best | C19: Footballers | D19: Northern Irish forward, football legend | E19: male | F19: Northern Ireland | G19: 1946 | H19: 60 | I19: =FALSE() | J19: =TRUE() | K19: Footballer | L19: Football | M19: Manchester United | N19: Premier League | O19: Forward | P19: =TRUE() | Q19: =FALSE() | V19: =FALSE() | W19: =TRUE() | AQ19: =TRUE()
A20: fb-buffon | B20: Gianluigi Buffon | C20: Footballers | D20: Italian goalkeeper, retired | E20: male | F20: Italy | G20: 1978 | H20: 60 | I20: =FALSE() | J20: =TRUE() | K20: Footballer | L20: Football | M20: Juventus | N20: Serie A | O20: Goalkeeper | P20: =TRUE() | Q20: =TRUE() | V20: =TRUE() | W20: =FALSE() | AQ20: =TRUE()
A21: fb-kane | B21: Harry Kane | C21: Footballers | D21: English forward, Bayern Munich | E21: male | F21: England | G21: 1993 | H21: 60 | I21: =TRUE() | J21: =FALSE() | K21: Footballer | L21: Football | M21: Bayern Munich | N21: Bundesliga | O21: Forward | P21: =TRUE() | Q21: =TRUE() | V21: =FALSE() | W21: =FALSE() | AP21: =TRUE() | AQ21: =TRUE()
A22: fb-casillas | B22: Iker Casillas | C22: Footballers | D22: Spanish goalkeeper, retired | E22: male | F22: Spain | G22: 1981 | H22: 60 | I22: =FALSE() | J22: =TRUE() | K22: Footballer | L22: Football | M22: Real Madrid | N22: La Liga | O22: Goalkeeper | P22: =TRUE() | Q22: =TRUE() | V22: =TRUE() | W22: =TRUE() | AQ22: =TRUE()
A23: fb-cruyff | B23: Johan Cruyff | C23: Footballers | D23: Dutch football legend | E23: male | F23: Netherlands | G23: 1947 | H23: 60 | I23: =FALSE() | J23: =TRUE() | K23: Footballer | L23: Football | M23: Ajax | N23: Eredivisie | O23: Forward | P23: =TRUE() | Q23: =TRUE() | V23: =FALSE() | W23: =TRUE() | AQ23: =TRUE()
A24: fb-bellingham | B24: Jude Bellingham | C24: Footballers | D24: English midfielder, Real Madrid | E24: male | F24: England | G24: 2003 | H24: 60 | I24: =TRUE() | J24: =FALSE() | K24: Footballer | L24: Football | M24: Real Madrid | N24: La Liga | O24: Midfielder | P24: =TRUE() | Q24: =FALSE() | V24: =FALSE() | W24: =TRUE() | AP24: =TRUE() | AQ24: =TRUE()
A25: fb-benzema | B25: Karim Benzema | C25: Footballers | D25: French forward, Al-Ittihad | E25: male | F25: France | G25: 1987 | H25: 60 | I25: =TRUE() | J25: =FALSE() | K25: Footballer | L25: Football | M25: Al-Ittihad | N25: Saudi Pro League | O25: Forward | P25: =TRUE() | Q25: =FALSE() | V25: =TRUE() | W25: =TRUE() | AQ25: =TRUE()
A26: fb-debruyne | B26: Kevin De Bruyne | C26: Footballers | D26: Belgian midfielder | E26: male | F26: Belgium | G26: 1991 | H26: 60 | I26: =TRUE() | J26: =FALSE() | K26: Footballer | L26: Football | M26: Napoli | N26: Serie A | O26: Midfielder | P26: =TRUE() | Q26: =TRUE() | V26: =FALSE() | W26: =TRUE() | AQ26: =TRUE()
A27: fb-mbappe | B27: Kylian Mbappé | C27: Footballers | D27: French forward, Real Madrid | E27: male | F27: France | G27: 1998 | H27: 92 | I27: =TRUE() | J27: =FALSE() | K27: Footballer | L27: Football | M27: Real Madrid | N27: La Liga | O27: Forward | P27: =TRUE() | Q27: =TRUE() | V27: =TRUE() | W27: =FALSE() | AQ27: =TRUE()
A28: fb-messi | B28: Lionel Messi | C28: Footballers | D28: Argentine forward, Inter Miami CF | E28: male | F28: Argentina | G28: 1987 | H28: 99 | I28: =TRUE() | J28: =FALSE() | K28: Footballer | L28: Football | M28: Inter Miami CF | N28: MLS | O28: Forward | P28: =TRUE() | Q28: =TRUE() | V28: =TRUE() | W28: =TRUE() | AQ28: =FALSE()
A29: fb-suarez | B29: Luis Suárez | C29: Footballers | D29: Uruguayan forward | E29: male | F29: Uruguay | G29: 1987 | H29: 60 | I29: =TRUE() | J29: =FALSE() | K29: Footballer | L29: Football | M29: Inter Miami CF | N29: MLS | O29: Forward | P29: =TRUE() | Q29: =FALSE() | V29: =FALSE() | W29: =TRUE() | AQ29: =FALSE()
A30: fb-modric | B30: Luka Modrić | C30: Footballers | D30: Croatian midfielder, Real Madrid | E30: male | F30: Croatia | G30: 1985 | H30: 60 | I30: =TRUE() | J30: =FALSE() | K30: Footballer | L30: Football | M30: Real Madrid | N30: La Liga | O30: Midfielder | P30: =TRUE() | Q30: =TRUE() | V30: =FALSE() | W30: =TRUE() | AQ30: =TRUE()
A31: fb-neuer | B31: Manuel Neuer | C31: Footballers | D31: German goalkeeper, Bayern Munich | E31: male | F31: Germany | G31: 1986 | H31: 60 | I31: =TRUE() | J31: =FALSE() | K31: Footballer | L31: Football | M31: Bayern Munich | N31: Bundesliga | O31: Goalkeeper | P31: =TRUE() | Q31: =TRUE() | V31: =TRUE() | W31: =TRUE() | AQ31: =TRUE()
A32: fb-marta | B32: Marta | C32: Footballers | D32: Brazilian forward, women's football icon | E32: female | F32: Brazil | G32: 1986 | H32: 60 | I32: =TRUE() | J32: =FALSE() | K32: Footballer | L32: Football | M32: Orlando Pride | N32: NWSL | O32: Forward | P32: =TRUE() | Q32: =TRUE() | V32: =FALSE() | AQ32: =FALSE()
A33: fb-rapinoe | B33: Megan Rapinoe | C33: Footballers | D33: American forward, women's football, retired | E33: female | F33: USA | G33: 1985 | H33: 60 | I33: =FALSE() | J33: =TRUE() | K33: Footballer | L33: Football | M33: OL Reign | N33: NWSL | O33: Forward | P33: =TRUE() | Q33: =TRUE() | V33: =TRUE() | AO33: =TRUE() | AQ33: =FALSE()
A34: fb-salah | B34: Mohamed Salah | C34: Footballers | D34: Egyptian forward, Liverpool FC | E34: male | F34: Egypt | G34: 1992 | H34: 60 | I34: =TRUE() | J34: =FALSE() | K34: Footballer | L34: Football | M34: Liverpool FC | N34: Premier League | O34: Forward | P34: =TRUE() | Q34: =TRUE() | V34: =FALSE() | W34: =TRUE() | AQ34: =FALSE()
A35: fb-kante | B35: N'Golo Kanté | C35: Footballers | D35: French midfielder, Al-Ittihad | E35: male | F35: France | G35: 1991 | H35: 60 | I35: =TRUE() | J35: =FALSE() | K35: Footballer | L35: Football | M35: Al-Ittihad | N35: Saudi Pro League | O35: Midfielder | P35: =TRUE() | Q35: =FALSE() | V35: =TRUE() | W35: =TRUE() | AQ35: =TRUE()
A36: fb-neymar | B36: Neymar Jr. | C36: Footballers | D36: Brazilian forward, Santos FC | E36: male | F36: Brazil | G36: 1992 | H36: 90 | I36: =TRUE() | J36: =FALSE() | K36: Footballer | L36: Football | M36: Santos FC | N36: Brasileirão | O36: Forward | P36: =TRUE() | Q36: =FALSE() | V36: =FALSE() | W36: =TRUE() | AQ36: =FALSE()
A37: fb-maldini | B37: Paolo Maldini | C37: Footballers | D37: Italian defender, retired | E37: male | F37: Italy | G37: 1968 | H37: 60 | I37: =FALSE() | J37: =TRUE() | K37: Footballer | L37: Football | M37: AC Milan | N37: Serie A | O37: Defender | P37: =TRUE() | Q37: =TRUE() | V37: =FALSE() | W37: =TRUE() | AQ37: =TRUE()
A38: fb-pele | B38: Pelé | C38: Footballers | D38: Brazilian football legend | E38: male | F38: Brazil | G38: 1940 | H38: 96 | I38: =FALSE() | J38: =TRUE() | K38: Footballer | L38: Football | M38: Santos FC | N38: Brasileirão | O38: Forward | P38: =TRUE() | Q38: =TRUE() | V38: =TRUE() | W38: =FALSE() | AQ38: =FALSE()
A39: fb-mahrez | B39: Riyad Mahrez | C39: Footballers | D39: Algerian forward | E39: male | F39: Algeria | G39: 1991 | H39: 60 | I39: =TRUE() | J39: =FALSE() | K39: Footballer | L39: Football | M39: Al-Ahli | N39: Saudi Pro League | O39: Forward | P39: =TRUE() | Q39: =TRUE() | V39: =FALSE() | W39: =TRUE() | AQ39: =FALSE()
A40: fb-lewandowski | B40: Robert Lewandowski | C40: Footballers | D40: Polish forward, FC Barcelona | E40: male | F40: Poland | G40: 1988 | H40: 60 | I40: =TRUE() | J40: =FALSE() | K40: Footballer | L40: Football | M40: FC Barcelona | N40: La Liga | O40: Forward | P40: =TRUE() | Q40: =TRUE() | V40: =FALSE() | W40: =TRUE() | AQ40: =TRUE()
A41: fb-ronaldinho | B41: Ronaldinho | C41: Footballers | D41: Brazilian former forward | E41: male | F41: Brazil | G41: 1980 | H41: 86 | I41: =FALSE() | J41: =TRUE() | K41: Footballer | L41: Football | M41: FC Barcelona | N41: La Liga | O41: Forward | P41: =TRUE() | Q41: =FALSE() | V41: =TRUE() | W41: =TRUE() | AQ41: =FALSE()
A42: fb-ronaldo-r9 | B42: Ronaldo Nazário | C42: Footballers | D42: Brazilian former forward, now club owner | E42: male | F42: Brazil | G42: 1976 | H42: 60 | I42: =FALSE() | J42: =TRUE() | K42: Footballer; Entrepreneur | L42: Football | M42: Real Madrid | N42: La Liga | O42: Forward | P42: =TRUE() | Q42: =FALSE() | V42: =TRUE() | W42: =FALSE() | AJ42: =TRUE() | AQ42: =FALSE()
A43: fb-mane | B43: Sadio Mané | C43: Footballers | D43: Senegalese forward | E43: male | F43: Senegal | G43: 1992 | H43: 60 | I43: =TRUE() | J43: =FALSE() | K43: Footballer | L43: Football | M43: Al-Nassr | N43: Saudi Pro League | O43: Forward | P43: =TRUE() | Q43: =TRUE() | V43: =FALSE() | W43: =TRUE() | AQ43: =FALSE()
A44: fb-samkerr | B44: Sam Kerr | C44: Footballers | D44: Australian forward, women's football | E44: female | F44: Australia | G44: 1993 | H44: 60 | I44: =TRUE() | J44: =FALSE() | K44: Footballer | L44: Football | M44: Chelsea FC | N44: Women's Super League | O44: Forward | P44: =TRUE() | Q44: =TRUE() | V44: =FALSE() | AQ44: =FALSE()
A45: fb-eto | B45: Samuel Eto'o | C45: Footballers | D45: Cameroonian forward, retired | E45: male | F45: Cameroon | G45: 1981 | H45: 60 | I45: =FALSE() | J45: =TRUE() | K45: Footballer | L45: Football | M45: FC Barcelona | N45: La Liga | O45: Forward | P45: =TRUE() | Q45: =TRUE() | V45: =FALSE() | W45: =TRUE() | AQ45: =FALSE()
A46: fb-sergioramos | B46: Sergio Ramos | C46: Footballers | D46: Spanish defender | E46: male | F46: Spain | G46: 1986 | H46: 60 | I46: =TRUE() | J46: =FALSE() | K46: Footballer | L46: Football | M46: Monterrey | N46: Liga MX | O46: Defender | P46: =TRUE() | Q46: =TRUE() | V46: =TRUE() | W46: =TRUE() | AQ46: =TRUE()
A47: fb-son | B47: Son Heung-min | C47: Footballers | D47: South Korean forward, Tottenham Hotspur | E47: male | F47: South Korea | G47: 1992 | H47: 60 | I47: =TRUE() | J47: =FALSE() | K47: Footballer | L47: Football | M47: Tottenham Hotspur | N47: Premier League | O47: Forward | P47: =TRUE() | Q47: =TRUE() | V47: =FALSE() | W47: =FALSE() | AQ47: =FALSE()
A48: fb-courtois | B48: Thibaut Courtois | C48: Footballers | D48: Belgian goalkeeper, Real Madrid | E48: male | F48: Belgium | G48: 1992 | H48: 60 | I48: =TRUE() | J48: =FALSE() | K48: Footballer | L48: Football | M48: Real Madrid | N48: La Liga | O48: Goalkeeper | P48: =TRUE() | Q48: =FALSE() | V48: =FALSE() | W48: =TRUE() | AQ48: =TRUE()
A49: fb-henry | B49: Thierry Henry | C49: Footballers | D49: French former forward, now pundit | E49: male | F49: France | G49: 1977 | H49: 60 | I49: =FALSE() | J49: =TRUE() | K49: Footballer | L49: Football | M49: Arsenal FC | N49: Premier League | O49: Forward | P49: =TRUE() | Q49: =TRUE() | V49: =TRUE() | W49: =TRUE() | AQ49: =TRUE()
A50: fb-kroos | B50: Toni Kroos | C50: Footballers | D50: German midfielder, retired | E50: male | F50: Germany | G50: 1990 | H50: 60 | I50: =FALSE() | J50: =TRUE() | K50: Footballer | L50: Football | M50: Real Madrid | N50: La Liga | O50: Midfielder | P50: =TRUE() | Q50: =FALSE() | V50: =TRUE() | W50: =TRUE() | AQ50: =TRUE()
A51: fb-osimhen | B51: Victor Osimhen | C51: Footballers | D51: Nigerian forward | E51: male | F51: Nigeria | G51: 1998 | H51: 60 | I51: =TRUE() | J51: =FALSE() | K51: Footballer | L51: Football | M51: Galatasaray | N51: Süper Lig | O51: Forward | P51: =TRUE() | Q51: =FALSE() | V51: =FALSE() | W51: =FALSE() | AQ51: =FALSE()
A52: fb-vinicius | B52: Vinícius Júnior | C52: Footballers | D52: Brazilian forward, Real Madrid | E52: male | F52: Brazil | G52: 2000 | H52: 60 | I52: =TRUE() | J52: =FALSE() | K52: Footballer | L52: Football | M52: Real Madrid | N52: La Liga | O52: Forward | P52: =TRUE() | Q52: =FALSE() | V52: =FALSE() | W52: =TRUE() | AQ52: =FALSE()
A53: fb-vandijk | B53: Virgil van Dijk | C53: Footballers | D53: Dutch defender, Liverpool FC | E53: male | F53: Netherlands | G53: 1991 | H53: 60 | I53: =TRUE() | J53: =FALSE() | K53: Footballer | L53: Football | M53: Liverpool FC | N53: Premier League | O53: Defender | P53: =TRUE() | Q53: =TRUE() | V53: =FALSE() | W53: =TRUE() | AQ53: =TRUE()
A54: fb-rooney | B54: Wayne Rooney | C54: Footballers | D54: English former forward, now manager | E54: male | F54: England | G54: 1985 | H54: 60 | I54: =FALSE() | J54: =TRUE() | K54: Footballer; Manager | L54: Football | M54: Manchester United | N54: Premier League | O54: Forward | P54: =TRUE() | Q54: =TRUE() | V54: =FALSE() | W54: =TRUE() | AP54: =TRUE() | AQ54: =TRUE()
A55: fb-xavi | B55: Xavi Hernández | C55: Footballers | D55: Spanish former midfielder, now manager | E55: male | F55: Spain | G55: 1980 | H55: 60 | I55: =FALSE() | J55: =TRUE() | K55: Footballer; Manager | L55: Football | M55: FC Barcelona | N55: La Liga | O55: Midfielder | P55: =TRUE() | Q55: =TRUE() | V55: =TRUE() | W55: =TRUE() | AQ55: =TRUE()
A56: fb-yayatoure | B56: Yaya Touré | C56: Footballers | D56: Ivorian midfielder, retired | E56: male | F56: Ivory Coast | G56: 1983 | H56: 60 | I56: =FALSE() | J56: =TRUE() | K56: Footballer | L56: Football | M56: Manchester City | N56: Premier League | O56: Midfielder | P56: =TRUE() | Q56: =TRUE() | V56: =FALSE() | W56: =TRUE() | AQ56: =FALSE()
A57: fb-zidane | B57: Zinedine Zidane | C57: Footballers | D57: French football legend, former manager | E57: male | F57: France | G57: 1972 | H57: 88 | I57: =FALSE() | J57: =TRUE() | K57: Footballer; Manager | L57: Football | M57: Real Madrid | N57: La Liga | O57: Midfielder | P57: =TRUE() | Q57: =TRUE() | V57: =TRUE() | W57: =TRUE() | AQ57: =TRUE()
A58: fb-zlatan | B58: Zlatan Ibrahimović | C58: Footballers | D58: Swedish forward, retired | E58: male | F58: Sweden | G58: 1981 | H58: 60 | I58: =FALSE() | J58: =TRUE() | K58: Footballer | L58: Football | M58: AC Milan | N58: Serie A | O58: Forward | P58: =TRUE() | Q58: =TRUE() | V58: =FALSE() | W58: =FALSE() | AQ58: =TRUE()
A59: cr-abd | B59: AB de Villiers | C59: Cricketers | D59: South African batsman, retired | E59: male | F59: South Africa | G59: 1984 | H59: 60 | I59: =FALSE() | J59: =TRUE() | K59: Cricketer | L59: Cricket | M59: Royal Challengers Bengaluru | N59: IPL | P59: =TRUE() | Q59: =FALSE() | R59: =TRUE() | S59: =FALSE() | T59: =FALSE() | U59: =TRUE() | V59: =FALSE() | AN59: =FALSE()
A60: cr-gilchrist | B60: Adam Gilchrist | C60: Cricketers | D60: Australian wicketkeeper-batsman, retired | E60: male | F60: Australia | G60: 1971 | H60: 60 | I60: =FALSE() | J60: =TRUE() | K60: Cricketer | L60: Cricket | M60: Australia | N60: International | P60: =TRUE() | Q60: =FALSE() | R60: =TRUE() | S60: =FALSE() | T60: =FALSE() | U60: =TRUE() | V60: =TRUE() | AN60: =FALSE()
A61: cr-andrerussell | B61: Andre Russell | C61: Cricketers | D61: West Indian all-rounder | E61: male | F61: West Indies | G61: 1988 | H61: 60 | I61: =TRUE() | J61: =FALSE() | K61: Cricketer | L61: Cricket | M61: Kolkata Knight Riders | N61: IPL | P61: =TRUE() | Q61: =FALSE() | R61: =TRUE() | S61: =TRUE() | T61: =TRUE() | U61: =FALSE() | V61: =TRUE() | AN61: =FALSE()
A62: cr-flintoff | B62: Andrew Flintoff | C62: Cricketers | D62: English all-rounder, retired | E62: male | F62: England | G62: 1977 | H62: 60 | I62: =FALSE() | J62: =TRUE() | K62: Cricketer | L62: Cricket | M62: England | N62: International | P62: =TRUE() | Q62: =FALSE() | R62: =TRUE() | S62: =TRUE() | T62: =TRUE() | U62: =FALSE() | V62: =FALSE() | AP62: =TRUE() | AQ62: =TRUE()
A63: cr-babar | B63: Babar Azam | C63: Cricketers | D63: Pakistani batsman | E63: male | F63: Pakistan | G63: 1994 | H63: 85 | I63: =TRUE() | J63: =FALSE() | K63: Cricketer | L63: Cricket | M63: Pakistan | N63: PSL | P63: =TRUE() | Q63: =TRUE() | R63: =TRUE() | S63: =FALSE() | T63: =FALSE() | U63: =FALSE() | V63: =FALSE() | AN63: =FALSE()
A64: cr-stokes | B64: Ben Stokes | C64: Cricketers | D64: English all-rounder | E64: male | F64: England | G64: 1991 | H64: 60 | I64: =TRUE() | J64: =FALSE() | K64: Cricketer | L64: Cricket | M64: England | N64: International | P64: =TRUE() | Q64: =TRUE() | R64: =TRUE() | S64: =TRUE() | T64: =TRUE() | U64: =FALSE() | V64: =TRUE() | AP64: =TRUE() | AQ64: =TRUE()
A65: cr-brettlee | B65: Brett Lee | C65: Cricketers | D65: Australian fast bowler, retired | E65: male | F65: Australia | G65: 1976 | H65: 60 | I65: =FALSE() | J65: =TRUE() | K65: Cricketer | L65: Cricket | M65: Australia | N65: International | P65: =TRUE() | Q65: =FALSE() | R65: =FALSE() | S65: =TRUE() | T65: =FALSE() | U65: =FALSE() | V65: =TRUE() | AN65: =FALSE()
A66: cr-lara | B66: Brian Lara | C66: Cricketers | D66: West Indian batting legend | E66: male | F66: West Indies | G66: 1969 | H66: 85 | I66: =FALSE() | J66: =TRUE() | K66: Cricketer | L66: Cricket | M66: West Indies | N66: International | P66: =TRUE() | Q66: =TRUE() | R66: =TRUE() | S66: =FALSE() | T66: =FALSE() | U66: =FALSE() | V66: =FALSE() | AN66: =FALSE()
A67: cr-gayle | B67: Chris Gayle | C67: Cricketers | D67: West Indian batsman, retired | E67: male | F67: West Indies | G67: 1979 | H67: 60 | I67: =FALSE() | J67: =TRUE() | K67: Cricketer | L67: Cricket | M67: West Indies | N67: IPL | P67: =TRUE() | Q67: =TRUE() | R67: =TRUE() | S67: =FALSE() | T67: =FALSE() | U67: =FALSE() | V67: =TRUE() | AN67: =FALSE()
A68: cr-ambrose | B68: Curtly Ambrose | C68: Cricketers | D68: West Indian fast bowler, retired legend | E68: male | F68: West Indies | G68: 1963 | H68: 60 | I68: =FALSE() | J68: =TRUE() | K68: Cricketer | L68: Cricket | M68: West Indies | N68: International | P68: =TRUE() | Q68: =FALSE() | R68: =FALSE() | S68: =TRUE() | T68: =FALSE() | U68: =FALSE() | V68: =FALSE() | AN68: =FALSE()
A69: cr-steyn | B69: Dale Steyn | C69: Cricketers | D69: South African fast bowler, retired | E69: male | F69: South Africa | G69: 1983 | H69: 60 | I69: =FALSE() | J69: =TRUE() | K69: Cricketer | L69: Cricket | M69: South Africa | N69: International | P69: =TRUE() | Q69: =FALSE() | R69: =FALSE() | S69: =TRUE() | T69: =FALSE() | U69: =FALSE() | V69: =FALSE() | AN69: =FALSE()
A70: cr-warner | B70: David Warner | C70: Cricketers | D70: Australian opening batsman | E70: male | F70: Australia | G70: 1986 | H70: 60 | I70: =TRUE() | J70: =FALSE() | K70: Cricketer | L70: Cricket | M70: Australia | N70: BBL | P70: =TRUE() | Q70: =FALSE() | R70: =TRUE() | S70: =FALSE() | T70: =FALSE() | U70: =FALSE() | V70: =TRUE() | AN70: =FALSE()
A71: cr-bravo | B71: Dwayne Bravo | C71: Cricketers | D71: West Indian all-rounder, retired from internationals | E71: male | F71: West Indies | G71: 1983 | H71: 60 | I71: =FALSE() | J71: =TRUE() | K71: Cricketer | L71: Cricket | M71: West Indies | N71: International | P71: =TRUE() | Q71: =TRUE() | R71: =TRUE() | S71: =TRUE() | T71: =TRUE() | U71: =FALSE() | V71: =TRUE() | AN71: =FALSE()
A72: cr-perry | B72: Ellyse Perry | C72: Cricketers | D72: Australian women's all-rounder | E72: female | F72: Australia | G72: 1990 | H72: 60 | I72: =TRUE() | J72: =FALSE() | K72: Cricketer | L72: Cricket | M72: Australia | N72: WBBL | P72: =TRUE() | Q72: =FALSE() | R72: =TRUE() | S72: =TRUE() | T72: =TRUE() | U72: =FALSE() | V72: =TRUE() | AN72: =FALSE()
A73: cr-morgan | B73: Eoin Morgan | C73: Cricketers | D73: English batsman, retired, former captain | E73: male | F73: England | G73: 1986 | H73: 60 | I73: =FALSE() | J73: =TRUE() | K73: Cricketer | L73: Cricket | M73: England | N73: International | P73: =TRUE() | Q73: =TRUE() | R73: =TRUE() | S73: =FALSE() | T73: =FALSE() | U73: =FALSE() | V73: =TRUE() | AP73: =TRUE() | AQ73: =TRUE()
A74: cr-faf | B74: Faf du Plessis | C74: Cricketers | D74: South African batsman | E74: male | F74: South Africa | G74: 1984 | H74: 60 | I74: =TRUE() | J74: =FALSE() | K74: Cricketer | L74: Cricket | M74: South Africa | N74: IPL | P74: =TRUE() | Q74: =TRUE() | R74: =TRUE() | S74: =FALSE() | T74: =FALSE() | U74: =FALSE() | V74: =FALSE() | AN74: =FALSE()
A75: cr-maxwell | B75: Glenn Maxwell | C75: Cricketers | D75: Australian all-rounder | E75: male | F75: Australia | G75: 1988 | H75: 60 | I75: =TRUE() | J75: =FALSE() | K75: Cricketer | L75: Cricket | M75: Australia | N75: BBL | P75: =TRUE() | Q75: =FALSE() | R75: =TRUE() | S75: =TRUE() | T75: =TRUE() | U75: =FALSE() | V75: =TRUE() | AN75: =FALSE()
A76: cr-hardik | B76: Hardik Pandya | C76: Cricketers | D76: Indian all-rounder, Mumbai Indians | E76: male | F76: India | G76: 1993 | H76: 60 | I76: =TRUE() | J76: =FALSE() | K76: Cricketer | L76: Cricket | M76: Mumbai Indians | N76: IPL | P76: =TRUE() | Q76: =TRUE() | R76: =FALSE() | S76: =TRUE() | T76: =TRUE() | U76: =FALSE() | V76: =TRUE() | AN76: =TRUE()
A77: cr-harmanpreet | B77: Harmanpreet Kaur | C77: Cricketers | D77: Indian women's batsman, captain | E77: female | F77: India | G77: 1989 | H77: 60 | I77: =TRUE() | J77: =FALSE() | K77: Cricketer | L77: Cricket | M77: India | N77: WPL | P77: =TRUE() | Q77: =TRUE() | R77: =TRUE() | S77: =FALSE() | T77: =FALSE() | U77: =FALSE() | V77: =FALSE() | AN77: =TRUE()
A78: cr-amla | B78: Hashim Amla | C78: Cricketers | D78: South African batsman, retired | E78: male | F78: South Africa | G78: 1983 | H78: 60 | I78: =FALSE() | J78: =TRUE() | K78: Cricketer | L78: Cricket | M78: South Africa | N78: International | P78: =TRUE() | Q78: =FALSE() | R78: =TRUE() | S78: =FALSE() | T78: =FALSE() | U78: =FALSE() | V78: =FALSE() | AN78: =FALSE()
A79: cr-inzamam | B79: Inzamam-ul-Haq | C79: Cricketers | D79: Pakistani batsman, retired | E79: male | F79: Pakistan | G79: 1970 | H79: 60 | I79: =FALSE() | J79: =TRUE() | K79: Cricketer | L79: Cricket | M79: Pakistan | N79: International | P79: =TRUE() | Q79: =TRUE() | R79: =TRUE() | S79: =FALSE() | T79: =FALSE() | U79: =FALSE() | V79: =TRUE() | AN79: =FALSE()
A80: cr-kallis | B80: Jacques Kallis | C80: Cricketers | D80: South African all-rounder, retired | E80: male | F80: South Africa | G80: 1975 | H80: 55 | I80: =FALSE() | J80: =TRUE() | K80: Cricketer | L80: Cricket | M80: South Africa | N80: International | P80: =TRUE() | Q80: =FALSE() | R80: =TRUE() | S80: =TRUE() | T80: =TRUE() | U80: =FALSE() | V80: =FALSE() | AN80: =FALSE()
A81: cr-bumrah | B81: Jasprit Bumrah | C81: Cricketers | D81: Indian fast bowler, Mumbai Indians | E81: male | F81: India | G81: 1993 | H81: 60 | I81: =TRUE() | J81: =FALSE() | K81: Cricketer | L81: Cricket | M81: Mumbai Indians | N81: IPL | P81: =TRUE() | Q81: =FALSE() | R81: =FALSE() | S81: =TRUE() | T81: =FALSE() | U81: =FALSE() | V81: =TRUE() | AN81: =TRUE()
A82: cr-root | B82: Joe Root | C82: Cricketers | D82: English batsman | E82: male | F82: England | G82: 1990 | H82: 60 | I82: =TRUE() | J82: =FALSE() | K82: Cricketer | L82: Cricket | M82: England | N82: International | P82: =TRUE() | Q82: =FALSE() | R82: =TRUE() | S82: =FALSE() | T82: =FALSE() | U82: =FALSE() | V82: =TRUE() | AP82: =TRUE() | AQ82: =TRUE()
A83: cr-buttler | B83: Jos Buttler | C83: Cricketers | D83: English wicketkeeper-batsman | E83: male | F83: England | G83: 1990 | H83: 60 | I83: =TRUE() | J83: =FALSE() | K83: Cricketer | L83: Cricket | M83: England | N83: The Hundred | P83: =TRUE() | Q83: =TRUE() | R83: =TRUE() | S83: =FALSE() | T83: =FALSE() | U83: =TRUE() | V83: =TRUE() | AP83: =TRUE() | AQ83: =TRUE()
A84: cr-klrahul | B84: KL Rahul | C84: Cricketers | D84: Indian batsman, Delhi Capitals | E84: male | F84: India | G84: 1992 | H84: 60 | I84: =TRUE() | J84: =FALSE() | K84: Cricketer | L84: Cricket | M84: Delhi Capitals | N84: IPL | P84: =TRUE() | Q84: =FALSE() | R84: =TRUE() | S84: =FALSE() | T84: =FALSE() | U84: =TRUE() | V84: =FALSE() | AN84: =TRUE()
A85: cr-williamson | B85: Kane Williamson | C85: Cricketers | D85: New Zealand batsman | E85: male | F85: New Zealand | G85: 1990 | H85: 60 | I85: =TRUE() | J85: =FALSE() | K85: Cricketer | L85: Cricket | M85: New Zealand | N85: International | P85: =TRUE() | Q85: =TRUE() | R85: =TRUE() | S85: =FALSE() | T85: =FALSE() | U85: =FALSE() | V85: =FALSE() | AN85: =FALSE()
A86: cr-sangakkara | B86: Kumar Sangakkara | C86: Cricketers | D86: Sri Lankan wicketkeeper-batsman, retired | E86: male | F86: Sri Lanka | G86: 1977 | H86: 60 | I86: =FALSE() | J86: =TRUE() | K86: Cricketer | L86: Cricket | M86: Sri Lanka | N86: International | P86: =TRUE() | Q86: =TRUE() | R86: =TRUE() | S86: =FALSE() | T86: =FALSE() | U86: =TRUE() | V86: =FALSE() | AN86: =FALSE()
A87: cr-malinga | B87: Lasith Malinga | C87: Cricketers | D87: Sri Lankan fast bowler, retired | E87: male | F87: Sri Lanka | G87: 1983 | H87: 60 | I87: =FALSE() | J87: =TRUE() | K87: Cricketer | L87: Cricket | M87: Sri Lanka | N87: International | P87: =TRUE() | Q87: =FALSE() | R87: =FALSE() | S87: =TRUE() | T87: =FALSE() | U87: =FALSE() | V87: =FALSE() | AN87: =FALSE()
A88: cr-dhoni | B88: MS Dhoni | C88: Cricketers | D88: Indian wicketkeeper-batsman, CSK | E88: male | F88: India | G88: 1981 | H88: 96 | I88: =TRUE() | J88: =FALSE() | K88: Cricketer | L88: Cricket | M88: Chennai Super Kings | N88: IPL | P88: =TRUE() | Q88: =TRUE() | R88: =TRUE() | S88: =FALSE() | T88: =FALSE() | U88: =TRUE() | V88: =TRUE() | AN88: =TRUE()
A89: cr-jayawardene | B89: Mahela Jayawardene | C89: Cricketers | D89: Sri Lankan batsman, retired | E89: male | F89: Sri Lanka | G89: 1977 | H89: 60 | I89: =FALSE() | J89: =TRUE() | K89: Cricketer | L89: Cricket | M89: Sri Lanka | N89: International | P89: =TRUE() | Q89: =TRUE() | R89: =TRUE() | S89: =FALSE() | T89: =FALSE() | U89: =FALSE() | V89: =FALSE() | AN89: =FALSE()
A90: cr-lanning | B90: Meg Lanning | C90: Cricketers | D90: Australian women's batsman, retired, former captain | E90: female | F90: Australia | G90: 1992 | H90: 60 | I90: =FALSE() | J90: =TRUE() | K90: Cricketer | L90: Cricket | M90: Australia | N90: International | P90: =TRUE() | Q90: =TRUE() | R90: =TRUE() | S90: =FALSE() | T90: =FALSE() | U90: =FALSE() | V90: =TRUE() | AN90: =FALSE()
A91: cr-clarke | B91: Michael Clarke | C91: Cricketers | D91: Australian batsman, retired, former captain | E91: male | F91: Australia | G91: 1981 | H91: 60 | I91: =FALSE() | J91: =TRUE() | K91: Cricketer | L91: Cricket | M91: Australia | N91: International | P91: =TRUE() | Q91: =TRUE() | R91: =TRUE() | S91: =FALSE() | T91: =FALSE() | U91: =FALSE() | V91: =TRUE() | AN91: =FALSE()
A92: cr-starc | B92: Mitchell Starc | C92: Cricketers | D92: Australian fast bowler | E92: male | F92: Australia | G92: 1990 | H92: 60 | I92: =TRUE() | J92: =FALSE() | K92: Cricketer | L92: Cricket | M92: Australia | N92: BBL | P92: =TRUE() | Q92: =FALSE() | R92: =FALSE() | S92: =TRUE() | T92: =FALSE() | U92: =FALSE() | V92: =TRUE() | AN92: =FALSE()
A93: cr-moeen | B93: Moeen Ali | C93: Cricketers | D93: English all-rounder | E93: male | F93: England | G93: 1987 | H93: 60 | I93: =TRUE() | J93: =FALSE() | K93: Cricketer | L93: Cricket | M93: England | N93: The Hundred | P93: =TRUE() | Q93: =FALSE() | R93: =TRUE() | S93: =TRUE() | T93: =TRUE() | U93: =FALSE() | V93: =TRUE() | AP93: =TRUE() | AQ93: =TRUE()
A94: cr-mushfiqur | B94: Mushfiqur Rahim | C94: Cricketers | D94: Bangladeshi wicketkeeper-batsman | E94: male | F94: Bangladesh | G94: 1987 | H94: 60 | I94: =TRUE() | J94: =FALSE() | K94: Cricketer | L94: Cricket | M94: Bangladesh | N94: International | P94: =TRUE() | Q94: =TRUE() | R94: =TRUE() | S94: =FALSE() | T94: =FALSE() | U94: =TRUE() | V94: =FALSE() | AN94: =FALSE()
A95: cr-murali | B95: Muttiah Muralitharan | C95: Cricketers | D95: Sri Lankan spin bowler, retired legend | E95: male | F95: Sri Lanka | G95: 1972 | H95: 60 | I95: =FALSE() | J95: =TRUE() | K95: Cricketer | L95: Cricket | M95: Sri Lanka | N95: International | P95: =TRUE() | Q95: =FALSE() | R95: =FALSE() | S95: =TRUE() | T95: =FALSE() | U95: =FALSE() | V95: =TRUE() | AN95: =FALSE()
A96: cr-cummins | B96: Pat Cummins | C96: Cricketers | D96: Australian fast bowler, captain | E96: male | F96: Australia | G96: 1993 | H96: 60 | I96: =TRUE() | J96: =FALSE() | K96: Cricketer | L96: Cricket | M96: Australia | N96: BBL | P96: =TRUE() | Q96: =TRUE() | R96: =FALSE() | S96: =TRUE() | T96: =FALSE() | U96: =FALSE() | V96: =TRUE() | AN96: =FALSE()
A97: cr-dravid | B97: Rahul Dravid | C97: Cricketers | D97: Indian batting legend, former head coach | E97: male | F97: India | G97: 1973 | H97: 60 | I97: =FALSE() | J97: =TRUE() | K97: Cricketer | L97: Cricket | M97: India | N97: International | P97: =TRUE() | Q97: =TRUE() | R97: =TRUE() | S97: =FALSE() | T97: =FALSE() | U97: =FALSE() | V97: =FALSE() | AN97: =TRUE()
A98: cr-rashid | B98: Rashid Khan | C98: Cricketers | D98: Afghan leg-spinner | E98: male | F98: Afghanistan | G98: 1998 | H98: 60 | I98: =TRUE() | J98: =FALSE() | K98: Cricketer | L98: Cricket | M98: Gujarat Titans | N98: IPL | P98: =TRUE() | Q98: =TRUE() | R98: =FALSE() | S98: =TRUE() | T98: =FALSE() | U98: =FALSE() | V98: =FALSE() | AN98: =FALSE()
A99: cr-jadeja | B99: Ravindra Jadeja | C99: Cricketers | D99: Indian all-rounder, CSK | E99: male | F99: India | G99: 1988 | H99: 60 | I99: =TRUE() | J99: =FALSE() | K99: Cricketer | L99: Cricket | M99: Chennai Super Kings | N99: IPL | P99: =TRUE() | Q99: =FALSE() | R99: =FALSE() | S99: =TRUE() | T99: =TRUE() | U99: =FALSE() | V99: =TRUE() | AN99: =TRUE()
A100: cr-ponting | B100: Ricky Ponting | C100: Cricketers | D100: Australian batting legend, former captain | E100: male | F100: Australia | G100: 1974 | H100: 60 | I100: =FALSE() | J100: =TRUE() | K100: Cricketer | L100: Cricket | M100: Australia | N100: International | P100: =TRUE() | Q100: =TRUE() | R100: =TRUE() | S100: =FALSE() | T100: =FALSE() | U100: =FALSE() | V100: =TRUE() | AN100: =FALSE()
...

Sheet Attribute Reference
A1: Attribute Reference — how characters are divided/classified
A2: Every yes/no question in the game is generated from one of these attributes. A blank cell for a character just means that attribute doesn't apply to their category (e.g. cricketers have no "marvel" field) — it's never a missing fact.
A4: Attribute | B4: What it means | C4: Used by categories
A5: IDENTITY
A6: gender | B6: male / female | C6: All categories with real people
A7: nationality | B7: Country/countries of origin (semicolon-separated if more than one) | C7: All real-person categories
A8: indian / american / british / european | B8: Quick regional flags used for broad identity questions | C8: All real-person categories
A9: birthYear | B9: Year of birth | C9: All real-person categories (where confidently known)
A10: CAREER / STATUS
A11: profession | B11: Primary job title(s) — Footballer, Actor, Politician, Scientist, etc. | C11: All categories
A12: active | B12: Still working/competing | C12: All real-person categories
A13: retired | B13: No longer active in their career | C13: Most real-person categories
A14: popularity | B14: 1-100 fame tier, used for Easy/Medium/Hard/Expert difficulty filtering. A subjective ranking judgment, not a factual claim. | C14: All characters
A15: SPORT
A16: sport | B16: Sport played (Football, Cricket, Basketball, Motorsport) | C16: Footballers, Cricketers, F1, Basketball, some Indian Celebrities
A17: team | B17: Current or most-associated club/team | C17: Footballers, Cricketers, F1, Basketball
A18: league | B18: Competition/league | C18: Footballers, Cricketers, F1, Basketball
A19: position | B19: Playing position (Forward, Guard, Goalkeeper, etc.) | C19: Footballers, Basketball
A20: athlete | B20: Is a professional athlete | C20: Sport categories + some Famous Personalities/Indian Celebrities
A21: captain | B21: Has captained their team/country | C21: Cricketers, Footballers, Indian Celebrities
A22: batsman / bowler / allRounder / wicketKeeper | B22: Cricket playing role | C22: Cricketers, some Indian Celebrities
A23: worldCupWinner | B23: Won a World Cup (football or cricket) | C23: Footballers, Cricketers, Indian Celebrities
A24: championsLeagueWinner | B24: Won a Champions League title | C24: Footballers
A25: olympicMedalist | B25: Won an Olympic medal | C25: Basketball, Indian Celebrities, Famous Personalities
A26: champion | B26: Won the top individual title in their sport (F1 Drivers' title, NBA/WNBA championship, etc.) — generic across sports rather than one field per sport | C26: F1 Drivers, Basketball, Indian Celebrities
A27: ENTERTAINMENT
A28: actor / actress | B28: Works primarily as an actor/actress | C28: Actors, Actresses, Indian Celebrities, some Famous Personalities
A29: singer | B29: Works primarily as a singer | C29: Singers, Indian Celebrities
A30: director | B30: Has directed films | C30: Actors, Actresses, Indian Celebrities, Famous Personalities
A31: comedy | B31: Primarily known for comedy | C31: Actors, Actresses, Fictional, Gamers, Indian Celebrities
A32: marvel | B32: Has appeared in the Marvel universe | C32: Actors, Actresses, Fictional
A33: oscarWinner | B33: Won a competitive Academy Award | C33: Actors, Actresses, Indian Celebrities
A34: grammyWinner | B34: Won a competitive Grammy (or Latin Grammy) | C34: Singers, Indian Celebrities
A35: soloArtist / bandMember | B35: Performs solo vs. as part of a group | C35: Singers
A36: BUSINESS
A37: entrepreneur | B37: Founded or leads a company | C37: Tech & Business, Famous Personalities, Indian Celebrities, some others
A38: founder | B38: Personally founded their company | C38: Tech & Business, Indian Celebrities
A39: billionaire | B39: Estimated net worth over $1B | C39: Tech & Business, Famous Personalities, Indian Celebrities
A40: streamer | B40: Works as a streamer/YouTuber | C40: Gamers & Streamers
A41: FICTIONAL-ONLY
A42: fictional | B42: Always true for this category, false/absent elsewhere | C42: Fictional Characters
A43: origin | B43: Medium the character originates from — comics / movies / games / literature / tv | C43: Fictional Characters
A44: heroOrVillain | B44: hero / villain / anti-hero | C44: Fictional Characters

Sheet Distribution
A1: Guess Who — Character Distribution
A2: All counts below are live formulas reading the Characters sheet (4624 characters, rows 2-4625).
A4: By Category
A5: Category | B5: Characters | C5: % of Total
A6: Footballers | B6: =COUNTIF(Characters!$C$2:$C$4625,A6) | C6: =B6/4624
A7: Cricketers | B7: =COUNTIF(Characters!$C$2:$C$4625,A7) | C7: =B7/4624
A8: Actors | B8: =COUNTIF(Characters!$C$2:$C$4625,A8) | C8: =B8/4624
A9: Actresses | B9: =COUNTIF(Characters!$C$2:$C$4625,A9) | C9: =B9/4624
A10: Singers | B10: =COUNTIF(Characters!$C$2:$C$4625,A10) | C10: =B10/4624
A11: Famous Personalities | B11: =COUNTIF(Characters!$C$2:$C$4625,A11) | C11: =B11/4624
A12: F1 Drivers | B12: =COUNTIF(Characters!$C$2:$C$4625,A12) | C12: =B12/4624
A13: Basketball Players | B13: =COUNTIF(Characters!$C$2:$C$4625,A13) | C13: =B13/4624
A14: Gamers & Streamers | B14: =COUNTIF(Characters!$C$2:$C$4625,A14) | C14: =B14/4624
A15: Tech & Business | B15: =COUNTIF(Characters!$C$2:$C$4625,A15) | C15: =B15/4624
A16: Fictional Characters | B16: =COUNTIF(Characters!$C$2:$C$4625,A16) | C16: =B16/4624
A17: Indian Celebrities | B17: =COUNTIF(Characters!$C$2:$C$4625,A17) | C17: =B17/4624
A18: Total | B18: =SUM(B6:B17) | C18: =B18/4624
A21: By Gender
A22: Gender | B22: Characters | C22: % of Total
A23: Male | B23: =COUNTIF(Characters!$E$2:$E$4625,"male") | C23: =B23/4624
A24: Female | B24: =COUNTIF(Characters!$E$2:$E$4625,"female") | C24: =B24/4624
A25: Unspecified (fictional, historical) | B25: =4624-SUM(B23:B24) | C25: =B25/4624
A28: Active vs. Retired (where tracked)
A29: Status | B29: Characters
A30: Active | B30: =COUNTIF(Characters!$I$2:$I$4625,TRUE())
A31: Retired | B31: =COUNTIF(Characters!$J$2:$J$4625,TRUE())
A34: By Popularity Tier (difficulty filtering)
A35: Tier | B35: Characters | C35: Popularity Range
A36: Easy-eligible | B36: =COUNTIFS(Characters!$H$2:$H$4625,">="&75,Characters!$H$2:$H$4625,"<="&100) | C36: 75-100
A37: Medium-eligible | B37: =COUNTIFS(Characters!$H$2:$H$4625,">="&55,Characters!$H$2:$H$4625,"<="&74) | C37: 55-74
A38: Hard-eligible | B38: =COUNTIFS(Characters!$H$2:$H$4625,">="&35,Characters!$H$2:$H$4625,"<="&54) | C38: 35-54
A39: Expert-only (deep cuts) | B39: =COUNTIFS(Characters!$H$2:$H$4625,">="&0,Characters!$H$2:$H$4625,"<="&34) | C39: 0-34
A42: By Decade of Birth (real people only)
A43: Decade | B43: Characters
A44: 1860s | B44: =COUNTIFS(Characters!$G$2:$G$4625,">="&1860,Characters!$G$2:$G$4625,"<="&1869)
A45: 1870s | B45: =COUNTIFS(Characters!$G$2:$G$4625,">="&1870,Characters!$G$2:$G$4625,"<="&1879)
A46: 1880s | B46: =COUNTIFS(Characters!$G$2:$G$4625,">="&1880,Characters!$G$2:$G$4625,"<="&1889)
A47: 1890s | B47: =COUNTIFS(Characters!$G$2:$G$4625,">="&1890,Characters!$G$2:$G$4625,"<="&1899)
A48: 1900s | B48: =COUNTIFS(Characters!$G$2:$G$4625,">="&1900,Characters!$G$2:$G$4625,"<="&1909)
A49: 1910s | B49: =COUNTIFS(Characters!$G$2:$G$4625,">="&1910,Characters!$G$2:$G$4625,"<="&1919)
A50: 1920s | B50: =COUNTIFS(Characters!$G$2:$G$4625,">="&1920,Characters!$G$2:$G$4625,"<="&1929)
A51: 1930s | B51: =COUNTIFS(Characters!$G$2:$G$4625,">="&1930,Characters!$G$2:$G$4625,"<="&1939)
A52: 1940s | B52: =COUNTIFS(Characters!$G$2:$G$4625,">="&1940,Characters!$G$2:$G$4625,"<="&1949)
A53: 1950s | B53: =COUNTIFS(Characters!$G$2:$G$4625,">="&1950,Characters!$G$2:$G$4625,"<="&1959)
A54: 1960s | B54: =COUNTIFS(Characters!$G$2:$G$4625,">="&1960,Characters!$G$2:$G$4625,"<="&1969)
A55: 1970s | B55: =COUNTIFS(Characters!$G$2:$G$4625,">="&1970,Characters!$G$2:$G$4625,"<="&1979)
A56: 1980s | B56: =COUNTIFS(Characters!$G$2:$G$4625,">="&1980,Characters!$G$2:$G$4625,"<="&1989)
A57: 1990s | B57: =COUNTIFS(Characters!$G$2:$G$4625,">="&1990,Characters!$G$2:$G$4625,"<="&1999)
A58: 2000s | B58: =COUNTIFS(Characters!$G$2:$G$4625,">="&2000,Characters!$G$2:$G$4625,"<="&2009)
A59: 2010s | B59: =COUNTIFS(Characters!$G$2:$G$4625,">="&2010,Characters!$G$2:$G$4625,"<="&2019)
A62: Selected Nationalities
A63: Nationality | B63: Characters
A64: USA | B64: =COUNTIF(Characters!$F$2:$F$4625,"*USA*")
A65: India | B65: =COUNTIF(Characters!$F$2:$F$4625,"*India*")
A66: UK | B66: =COUNTIF(Characters!$F$2:$F$4625,"*UK*")
A67: Brazil | B67: =COUNTIF(Characters!$F$2:$F$4625,"*Brazil*")
A68: Australia | B68: =COUNTIF(Characters!$F$2:$F$4625,"*Australia*")
A69: France | B69: =COUNTIF(Characters!$F$2:$F$4625,"*France*")
A70: Spain | B70: =COUNTIF(Characters!$F$2:$F$4625,"*Spain*")
A71: Germany | B71: =COUNTIF(Characters!$F$2:$F$4625,"*Germany*")
A72: Pakistan | B72: =COUNTIF(Characters!$F$2:$F$4625,"*Pakistan*")
A73: West Indies | B73: =COUNTIF(Characters!$F$2:$F$4625,"*West Indies*")
A74: Sri Lanka | B74: =COUNTIF(Characters!$F$2:$F$4625,"*Sri Lanka*")
A75: South Africa | B75: =COUNTIF(Characters!$F$2:$F$4625,"*South Africa*")
A76: Canada | B76: =COUNTIF(Characters!$F$2:$F$4625,"*Canada*")
A77: Argentina | B77: =COUNTIF(Characters!$F$2:$F$4625,"*Argentina*")
A78: Italy | B78: =COUNTIF(Characters!$F$2:$F$4625,"*Italy*")
A79: Nigeria | B79: =COUNTIF(Characters!$F$2:$F$4625,"*Nigeria*")
A80: China | B80: =COUNTIF(Characters!$F$2:$F$4625,"*China*")
A81: Japan | B81: =COUNTIF(Characters!$F$2:$F$4625,"*Japan*")
A82: Note: counts are wildcard text matches, so a dual-nationality
A83: character (e.g. "Kenya; Mexico") is counted under both.
